fan_tools/__init__.py
fan_tools/aio_utils.py
fan_tools/const.py
fan_tools/container_utils.py
fan_tools/file_utils.py
fan_tools/image_utils.py
fan_tools/metrics.py
fan_tools/monitoring.py
fan_tools/profiler.py
fan_tools/sentry.py
fan_tools/unix.py
fan_tools/aws/__init__.py
fan_tools/aws/lambda_cleanup.py
fan_tools/backup/__init__.py
fan_tools/backup/gcloud.py
fan_tools/backup/s3.py
fan_tools/backup/utils.py
fan_tools/django/__init__.py
fan_tools/django/fields.py
fan_tools/django/log_requests.py
fan_tools/django/mail.py
fan_tools/django/models.py
fan_tools/django/url.py
fan_tools/django/contrib/__init__.py
fan_tools/django/contrib/postgres/__init__.py
fan_tools/django/contrib/postgres/indexes.py
fan_tools/django/contrib/postgres/models.py
fan_tools/django/contrib/postgres/operations.py
fan_tools/django/contrib/postgres/fields/__init__.py
fan_tools/django/contrib/postgres/fields/ltree.py
fan_tools/django/core/__init__.py
fan_tools/django/core/management.py
fan_tools/django/db/__init__.py
fan_tools/django/db/pgfields.py
fan_tools/django/db/utils.py
fan_tools/doc_utils/__init__.py
fan_tools/doc_utils/fan_sphinx/__init__.py
fan_tools/doc_utils/fan_sphinx/dyn.py
fan_tools/doc_utils/fan_sphinx/dyn_json.py
fan_tools/doc_utils/fan_sphinx/dyn_serializer.py
fan_tools/doc_utils/fan_sphinx/http_log.py
fan_tools/doc_utils/fan_sphinx/init.py
fan_tools/doc_utils/fan_sphinx/parse_mixin.py
fan_tools/drf/__init__.py
fan_tools/drf/asserts.py
fan_tools/drf/filters.py
fan_tools/drf/handlers.py
fan_tools/drf/pagination.py
fan_tools/drf/renderers.py
fan_tools/drf/serializers.py
fan_tools/drf/validation.py
fan_tools/fan_logging/__init__.py
fan_tools/fan_logging/handlers.py
fan_tools/generic/controller.py
fan_tools/generic/debug.py
fan_tools/mon_server/__init__.py
fan_tools/mon_server/certs.py
fan_tools/mon_server/gitlab_runners.py
fan_tools/mon_server/tests/__init__.py
fan_tools/otel/__init__.py
fan_tools/otel/django.py
fan_tools/otel/jaeger_tracing.py
fan_tools/otel/log.py
fan_tools-4.4.0.dist-info/METADATA
fan_tools-4.4.0.dist-info/WHEEL
fan_tools-4.4.0.dist-info/entry_points.txt
fan_tools-4.4.0.dist-info/licenses/LICENSE
fan_tools-4.4.0.dist-info/RECORD
