Metadata-Version: 2.1
Name: fan-tools
Version: 4.4.0
Summary: Various python stuff: testing, aio helpers, etc
Project-URL: github, http://github.com/micro-fan/fan_tools
Author-email: cybergrind <cybergind+pypi@gmail.com>
License-File: LICENSE
Keywords: asyncio,testing
Classifier: Development Status :: 5 - Production/Stable
Classifier: Intended Audience :: Developers
Classifier: License :: OSI Approved :: MIT License
Classifier: Operating System :: MacOS
Classifier: Operating System :: MacOS :: MacOS X
Classifier: Operating System :: POSIX
Classifier: Operating System :: POSIX :: Linux
Classifier: Operating System :: Unix
Classifier: Programming Language :: Python
Classifier: Programming Language :: Python :: 3.10
Classifier: Programming Language :: Python :: 3.11
Classifier: Programming Language :: Python :: 3.12
Classifier: Programming Language :: Python :: Implementation
Classifier: Programming Language :: Python :: Implementation :: CPython
Classifier: Topic :: Software Development
Classifier: Topic :: Software Development :: Libraries
Classifier: Topic :: Utilities
Requires-Dist: pyyaml>=3.12
Requires-Dist: typing-extensions>=4.4
Provides-Extra: aio-utils
Requires-Dist: aiopg; extra == 'aio-utils'
Requires-Dist: psycopg2-binary; extra == 'aio-utils'
Provides-Extra: doc-utils
Requires-Dist: djangorestframework~=3.12.0; extra == 'doc-utils'
Requires-Dist: docutils; extra == 'doc-utils'
Requires-Dist: rest-framework-dyn-serializer~=1.3.1; extra == 'doc-utils'
Provides-Extra: gcloud-backup
Requires-Dist: fan-tools[logging]; extra == 'gcloud-backup'
Requires-Dist: google-cloud-storage; extra == 'gcloud-backup'
Provides-Extra: gitlab-monitoring
Requires-Dist: python-gitlab==1.0.2; extra == 'gitlab-monitoring'
Provides-Extra: image-utils
Requires-Dist: pillow; extra == 'image-utils'
Provides-Extra: jaeger
Requires-Dist: opentelemetry-exporter-jaeger-thrift; extra == 'jaeger'
Provides-Extra: logging
Requires-Dist: python-json-logger==0.1.7; extra == 'logging'
Requires-Dist: safe-logger>=1.2.1; extra == 'logging'
Provides-Extra: monitoring
Requires-Dist: starlette; extra == 'monitoring'
Provides-Extra: otel
Requires-Dist: opentelemetry-instrumentation-django; extra == 'otel'
Requires-Dist: opentelemetry-instrumentation-psycopg2; extra == 'otel'
Provides-Extra: s3-backup
Requires-Dist: boto3; extra == 's3-backup'
Requires-Dist: fan-tools[logging]; extra == 's3-backup'
